{
  "asOf": "2026-07-01",
  "_note": "Inventory-facing grading-company registry. INTENTIONALLY broader than the pre-grader's tolerance set in grading.config.json: you can OWN a slab from any company, but the pre-grader only predicts grades for companies whose centering tolerances/fees are known (PSA/BGS/CGC/SGC/TAG). Do NOT wire the others into the grader without real tolerance data (Golden Rule 4).",
  "_fields": "code=short code stored on the item; label=display; scale/step=grade dropdown; subgrades=slab carries subgrades; certUrl=official verification page ({cert} substituted if present; omit if no public page); lookup=true means /api/cert can auto-fill card+grade from the cert number (PSA only today); certFormat=human hint; region=primary market; note=caveats; theme={bg,fg,accent} brand colours for the mini-slab badge (slabBadge in inventory.html).",
  "companies": [
    { "code": "PSA", "label": "PSA",                    "scale": "1-10",         "step": 1,   "subgrades": false, "lookup": true,  "certFormat": "8 digits",            "certUrl": "https://www.psacard.com/cert/{cert}",             "region": "US", "theme": { "bg": "#cf2e2e", "fg": "#ffffff", "accent": "#7a1416" } },
    { "code": "BGS", "label": "Beckett (BGS)",           "scale": "1-10 (0.5)",   "step": 0.5, "subgrades": true,  "lookup": false, "certFormat": "8-13 digits",         "certUrl": "https://www.beckett.com/grading/card-lookup",     "region": "US", "theme": { "bg": "#141414", "fg": "#e7c66b", "accent": "#b8912f" } },
    { "code": "CGC", "label": "CGC",                     "scale": "1-10 (0.5)",   "step": 0.5, "subgrades": false, "lookup": false, "certFormat": "7-12 digits",         "certUrl": "https://www.cgccards.com/certlookup/",            "region": "US", "theme": { "bg": "#0b3fa3", "fg": "#ffffff", "accent": "#072a6e" } },
    { "code": "SGC", "label": "SGC",                     "scale": "1-10 (0.5)",   "step": 0.5, "subgrades": false, "lookup": false, "certFormat": "7-8 digits",          "certUrl": "https://gosgc.com/",                              "region": "US", "theme": { "bg": "#101215", "fg": "#f2f2f2", "accent": "#4a4f57" } },
    { "code": "TAG", "label": "TAG",                     "scale": "1-10 (1000pt)","step": 0.5, "subgrades": true,  "lookup": false, "certFormat": "1 letter + 7 digits", "certUrl": "https://tagd.co/{cert}",                          "region": "US", "theme": { "bg": "#0f7d7a", "fg": "#ffffff", "accent": "#0a5a58" } },
    { "code": "ARK", "label": "ARK Grading",             "scale": "1-10",         "step": 0.5, "subgrades": false, "lookup": false, "certFormat": "cert / NFC / QR",     "certUrl": "https://arkgrading.com.au/",                      "region": "AU", "theme": { "bg": "#17102a", "fg": "#d6b4ff", "accent": "#6d4bd0" }, "note": "Verify by tapping the slab's NFC chip / scanning its QR — no cert-number web lookup." },
    { "code": "TCG", "label": "TCG Grading (AU)",        "scale": "1-10 (0.5)",   "step": 0.5, "subgrades": true,  "lookup": false, "certFormat": "serial on label (no spaces)", "certUrl": "https://tcggrading.com.au/pages/certification-1", "region": "AU", "theme": { "bg": "#16233f", "fg": "#ffd23f", "accent": "#0f1830" }, "note": "Grades Pokemon/One Piece/Yu-Gi-Oh/sports/sealed. Subgrades + slab photos for submissions from Jun 2025." },
    { "code": "CGA", "label": "Card Grading Australia (CGA)", "scale": "1-10",    "step": 0.5, "subgrades": false, "lookup": false, "certFormat": "grading number on tag", "certUrl": "https://www.cardgradingaustralia.com/verify/",  "region": "AU", "theme": { "bg": "#0c6b4f", "fg": "#ffffff", "accent": "#063d2d" }, "note": "Est. 2012; 1-10 grade backed by a 100-point internal scale." },
    { "code": "PCG", "label": "Premier Card Grading (AU/US)", "scale": "1-10 (0.5)", "step": 0.5, "subgrades": true, "lookup": false, "certFormat": "cert number", "certUrl": "https://www.pcgpopreport.com/", "region": "AU/US", "theme": { "bg": "#1a1a1a", "fg": "#cfcfcf", "accent": "#8a8a8a" }, "note": "The Western 'Premier Card Grading' — AU-HQ'd (PCG AUS, premiercardgrading.com.au) + US site (premiercardgrading.com), sharing the pcgpopreport.com registry. Distinct from PCGCN (the Chinese PCG)." },
    { "code": "PCGCN", "label": "PCG (China · pcgcard.cn)", "scale": "1-10 (0.5)", "step": 0.5, "subgrades": false, "lookup": false, "certFormat": "cert number (QR on slab)", "certUrl": "https://card.pcgcard.cn/h5/index.html#/pages/f/r?type=1&query={cert}", "region": "CN", "theme": { "bg": "#7c1220", "fg": "#f5d271", "accent": "#4d0b14" }, "note": "Chinese PCG grader (pcgcard.cn) — a separate company from the Western Premier Card Grading. The slab QR links to a per-card verification page; {cert} deep-links straight to it (confirmed via a scanned slab)." },
    { "code": "EMC", "label": "EMC — Encapsulated Memories Company", "scale": "1-10", "step": 1, "subgrades": false, "lookup": false, "certFormat": "cert number (e.g. #07)", "certUrl": null, "region": "US", "theme": { "bg": "#b93b2e", "fg": "#ffffff", "accent": "#7d241a" }, "note": "Boutique grader; full name confirmed off-slab ('Encapsulated Memories Company', PSA-style Gem Mint 10). No public online cert-lookup portal found — record manually / verify with the grader (a site at encapsulatedmemories.com appears related but is unconfirmed as the card grader)." },
    { "code": "JBH", "label": "Joyful Box House (JBH)", "scale": "1-10 (0.5)", "step": 0.5, "subgrades": true, "lookup": false, "certFormat": "cert number", "certUrl": "https://jbh130.com/", "region": "CN", "theme": { "bg": "#12539b", "fg": "#ffffff", "accent": "#0c3a6f" }, "note": "Chinese grader (盒乐屋); slab carries 4 subgrades (corners/edges/surface/centering) on a 0.5 scale. Grading via the MaiXiqi (mxiqi.com) platform; no standalone cert-number lookup portal found." }
  ]
}
